jamf_auth.py
jamf_api_auth-1.1.0.dist-info/LICENSE
jamf_api_auth-1.1.0.dist-info/METADATA
jamf_api_auth-1.1.0.dist-info/WHEEL
jamf_api_auth-1.1.0.dist-info/top_level.txt
jamf_api_auth-1.1.0.dist-info/RECORD
