Metadata-Version: 2.1
Name: jamf-api-auth
Version: 1.1.0
Summary: Provides automatically-refreshing token authentication for the Jamf Pro API to the Python Requests module.
License: MIT
Classifier: License :: OSI Approved :: MIT License
Classifier: Development Status :: 5 - Production/Stable
Classifier: Intended Audience :: Developers
Classifier: Topic :: Software Development :: Libraries
Requires-Python: >=3.6
License-File: LICENSE
Requires-Dist: requests
